<soap:Envelope xmlns:soap="http://schemas.xmlsoap.org/soap/envelope/"><soap:Body><ESBServerEnvelopeResponse xmlns="http://www.mze.cz/ESBServer/1.0" xmlns:ns2="http://sitewell.cz/lpis/schemas/LPI_GDP01A"><Service ID="LPI_GDP01A"/><Inquirer ID="LPIS" CorrelationID="716ab2ab-3823-456e-8187-ddf914a38147" Version="1.0" Timestamp="2020-08-01T22:10:11.004+02:00"/><ESBServer CorrelationID="716ab2ab-3823-456e-8187-ddf914a38147" Timestamp="2020-08-01T22:10:11.005+02:00"/><Data Content="xml"><ns2:Response><ns2:DATZMENYDPB>2020-05-11</ns2:DATZMENYDPB><ns2:DPB><ns2:IDDPB>12070164</ns2:IDDPB><ns2:CTVEREC>730-1100</ns2:CTVEREC><ns2:ZKOD>5403/7</ns2:ZKOD><ns2:STAV>UCINNY</ns2:STAV><ns2:STAVID>4</ns2:STAVID><ns2:UCINNOST_DLE_ZAKONA>2020-04-24</ns2:UCINNOST_DLE_ZAKONA><ns2:GEOMETRIE>POLYGON ((-735265.5477 -1104765.5955, -735269.8981 -1104765.9178, -735292.52 -1104764.7272, -735325.3284 -1104762.3459, -735383.8015 -1104757.1865, -735420.0677 -1104753.1508, -735500.2896 -1104743.4141, -735540.718 -1104738.1224, -735563.4 -1104734.5, -735571.656 -1104732.8448, -735577.9 -1104731, -735581.7747 -1104729.4902, -735585.5498 -1104728.5264, -735589.8689 -1104727.5071, -735591.6386 -1104727.2859, -735593.5188 -1104727.7283, -735596.4406 -1104728.9887, -735598.0281 -1104728.8123, -735598.7336 -1104728.1068, -735599.602 -1104725.848, -735600.0444 -1104723.4148, -735601.0398 -1104719.7649, -735602.92 -1104714.6772, -735608.1848 -1104703.1808, -735619.6 -1104680.1, -735624.2 -1104672.8, -735627.6 -1104669.6, -735630.6 -1104667.8, -735635.3 -1104666.2, -735645.8 -1104662.9, -735660.6435 -1104657.8786, -735672.0735 -1104654.7036, -735696.5 -1104649.4, -735726.1 -1104640.5, -735732.1 -1104639.1, -735734.5 -1104639.3, -735736.1 -1104640.6, -735739.1 -1104645.1, -735757.8886 -1104692.3049, -735763.1803 -1104704.123, -735765.8261 -1104708.1799, -735766.8845 -1104709.4146, -735768.2956 -1104709.7674, -735791.5789 -1104697.2438, -735800.5748 -1104690.541, -735808.1595 -1104683.6618, -735813.219 -1104676.3769, -735814.9388 -1104672.805, -735816.2617 -1104669.63, -735816.6586 -1104664.2061, -735814.6742 -1104654.1519, -735814.4096 -1104652.0352, -735814.6742 -1104650.58, -735815.6002 -1104648.4633, -735815.8648 -1104646.0821, -735814.7901 -1104643.9085, -735813.0867 -1104642.6425, -735807.9273 -1104642.2456, -735807.0012 -1104641.5842, -735805.2815 -1104638.4091, -735803.5617 -1104636.1602, -735799.9898 -1104632.456, -735799.8575 -1104631.0008, -735800.5189 -1104629.9425, -735804.3554 -1104627.2966, -735808.0596 -1104622.6664, -735809.6471 -1104619.8883, -735810.044 -1104617.9039, -735809.7101 -1104612.9522, -735809.2338 -1104611.0472, -735808.1226 -1104608.5072, -735806.3398 -1104606.6591, -735803.5617 -1104604.807, -735801.1804 -1104603.7487, -735799.5929 -1104603.0872, -735797.7408 -1104603.0872, -735795.7564 -1104603.881, -735786.6283 -1104613.0091, -735785.57 -1104613.5383, -735784.5116 -1104613.0091, -735782.6595 -1104607.4528, -735778.9554 -1104602.9549, -735778.5585 -1104601.7643, -735778.9554 -1104601.1028, -735780.4106 -1104600.3091, -735782.5272 -1104599.5153, -735786.0991 -1104596.7372, -735788.8773 -1104593.6945, -735790.7293 -1104591.1809, -735792.7137 -1104586.8153, -735794.1689 -1104583.1111, -735796.1533 -1104573.1892, -735796.9471 -1104571.4694, -735797.6085 -1104570.6757, -735799.196 -1104569.7496, -735804.0908 -1104567.3684, -735809.7794 -1104563.6642, -735811.3669 -1104561.6798, -735811.6315 -1104560.3569, -735811.3669 -1104559.034, -735807.0012 -1104553.7423, -735804.2231 -1104549.509, -735805.0169 -1104546.4663, -735805.9429 -1104543.159, -735807.6627 -1104540.5131, -735809.1179 -1104538.9256, -735811.1023 -1104537.2058, -735814.8065 -1104535.2214, -735826.7 -1104534.9, -735839.9096 -1104537.4351, -735853.3 -1104542.4, -735865.4 -1104548.5, -735877.8 -1104556.8, -735884 -1104564, -735898.6 -1104590.7, -735900.4 -1104592, -735901.5 -1104591.6, -735901.7 -1104589.6, -735900.8 -1104574.3, -735896.2 -1104552, -735896.5 -1104549.1, -735898.1 -1104547.5, -735900.8 -1104546.9, -735906.5 -1104547.4, -735933 -1104550.1, -735991.3204 -1104559.1359, -736010.688 -1104562.7871, -736019.4 -1104565.6, -736021.9 -1104567.7, -736023.5 -1104570.3, -736024.1 -1104575.3, -736023.1 -1104578.3, -736020.7 -1104581.6, -736009.5 -1104592, -735991.4 -1104609.8, -735978.2 -1104624.6, -735960.1 -1104649.3, -735956.4 -1104653.1, -735954.4 -1104654, -735952.6 -1104654, -735950.2 -1104652.8, -735931.9848 -1104630.0395, -735915.2 -1104610.9, -735911.9 -1104609.8, -735910 -1104610.2, -735908.5 -1104612, -735908.7 -1104613.9, -735921.8 -1104629, -735950.2 -1104663.1, -735950.7 -1104665.5, -735950.2 -1104667.9, -735939.5 -1104684, -735926.4 -1104699.1, -735917.2 -1104709.1, -735914.3 -1104711.7, -735911.9 -1104712.6, -735908.4 -1104712.8, -735890.8 -1104710.7, -735887.5 -1104711.2, -735884.8 -1104712.1, -735883.3 -1104713.2, -735881.1 -1104715.9, -735874.4802 -1104721.8549, -735871.9402 -1104722.9662, -735869.4002 -1104723.4424, -735850.0326 -1104724.7125, -735848.6039 -1104725.1887, -735847.3339 -1104726.4587, -735846.5401 -1104729.7925, -735846.6989 -1104731.6975, -735847.4926 -1104732.4912, -735849.2389 -1104732.9675, -735868.2889 -1104731.2212, -735871.1464 -1104731.5387, -735873.5277 -1104732.015, -735884.6566 -1104735.1145, -735888.3608 -1104737.4958, -735889.8 -1104739, -735890.9 -1104741.6, -735891.2 -1104743.2, -735890.4775 -1104745.6979, -735881.7 -1104762.1, -735879.8 -1104771.7, -735877.5 -1104780.4, -735874.3 -1104785.2, -735871.3 -1104787.8, -735852.3774 -1104795.1751, -735846.9534 -1104797.8209, -735843.1169 -1104801.2605, -735835.5763 -1104808.8012, -735831.343 -1104815.8126, -735826.845 -1104825.7345, -735824.8607 -1104839.096, -735823.2732 -1104842.6679, -735798.5 -1104870.5, -735783.675 -1104883.7803, -735770.8162 -1104892.9878, -735758.1162 -1104900.4491, -735747.6387 -1104903.4653, -735743.9874 -1104904.8941, -735735.7324 -1104910.1328, -735725.2549 -1104917.7528, -735703.3473 -1104937.7554, -735693.6636 -1104947.1216, -735678.5823 -1104964.4254, -735655.881 -1104982.2055, -735624.1309 -1105000.4618, -735589.5234 -1105014.7493, -735569 -1105022.7, -735567.5 -1105024.3, -735567.7 -1105028, -735569.5208 -1105029.5131, -735571.4258 -1105029.5131, -735573.9658 -1105028.8781, -735614.5463 -1105014.0732, -735644.9307 -1104999.4887, -735666.8 -1104985.1, -735673.5 -1104980.3, -735676.6 -1104978.5, -735678.8 -1104977.7, -735681.4 -1104977.5, -735683.9 -1104978.5, -735687.6 -1104981.6, -735690 -1104984.5, -735691.2 -1104986.6, -735691.3 -1104989.1, -735689.7 -1104992.6, -735665.3 -1105011.1, -735634.8 -1105032.4, -735625.3644 -1105037.9308, -735615.0457 -1105041.8995, -735560.6452 -1105059.8983, -735554.3762 -1105062.3729, -735551.0766 -1105063.1978, -735548.3705 -1105063.7277, -735546.5184 -1105064.5215, -735545.0632 -1105066.109, -735543.608 -1105069.9454, -735538.8684 -1105083.3249, -735532.7601 -1105111.4851, -735521.7798 -1105149.4529, -735520.8538 -1105151.5695, -735519.6632 -1105152.8925, -735518.0757 -1105153.6862, -735515.033 -1105153.8185, -735511.9902 -1105153.0248, -735508.0845 -1105150.7983, -735493.3371 -1105136.4883, -735483.6798 -1105121.8039, -735482.886 -1105121.1424, -735481.2985 -1105120.6132, -735479.0495 -1105120.7455, -735477.1975 -1105121.2747, -735475.7423 -1105122.4653, -735474.8162 -1105123.9205, -735474.5516 -1105125.6403, -735475.3454 -1105128.4185, -735485.3832 -1105143.1783, -735488.4423 -1105147.4685, -735489.1037 -1105149.7175, -735488.9714 -1105152.4956, -735489.0344 -1105155.5608, -735490.3044 -1105159.0533, -735492.2787 -1105161.3592, -735500.7454 -1105168.3706, -735514.1069 -1105175.3821, -735515.6944 -1105176.9696, -735516.4882 -1105178.5571, -735517.1496 -1105180.4092, -735517.5465 -1105182.7904, -735517.6788 -1105185.7009, -735517.2566 -1105188.4146, -735512.1423 -1105214.8108, -735506.5663 -1105253.1698, -735522.6 -1105176, -735526.6 -1105152.7, -735542.1 -1105091.2, -735544.401 -1105085, -735547.801 -1105078.101, -735551.201 -1105074, -735555.301 -1105070.2, -735560.401 -1105067.5, -735628.804 -1105038.9891, -735635.0847 -1105036.1806, -735643.181 -1105033.6406, -735649.531 -1105030.6243, -735680.9636 -1105010.6218, -735713 -1104985.801, -735725.5 -1104975.9, -735742.0824 -1104964.7429, -735750.1787 -1104957.9167, -735752.9 -1104955.1, -735756.9949 -1104952.4702, -735759.773 -1104951.4119, -735762.8157 -1104950.7504, -735765.3293 -1104950.6181, -735768.1074 -1104951.015, -735770.4887 -1104951.941, -735779.2199 -1104957.1004, -735787.8189 -1104963.3181, -735796.4179 -1104969.5359, -735813.3857 -1104988.0556, -735815.4494 -1104989.4843, -735817.5132 -1104989.8018, -735819.5769 -1104989.1668, -735825.7682 -1104982.8168, -735837.8332 -1104971.3868, -735839.262 -1104969.1643, -735839.7382 -1104967.5768, -735838.7513 -1104965.964, -735795.4 -1104913.2, -735794.3 -1104910.5, -735794.3 -1104907.4, -735795.6 -1104904.4, -735804.2231 -1104892.4097, -735815.9971 -1104874.0211, -735818.9075 -1104870.3169, -735821.7 -1104867.6, -735833.3273 -1104857.7492, -735843.3815 -1104846.6366, -735854.0972 -1104831.1585, -735876.3 -1104809.1, -735894.1 -1104794.3, -735903.5 -1104773.5, -735910.6 -1104762.9, -735917.9 -1104753.5, -735919.6 -1104751.9, -735922.2 -1104750.4, -735931.6202 -1104744.1104, -735936.2505 -1104740.6708, -735938.8963 -1104737.7604, -735947 -1104724.6, -735955.3 -1104709.3, -735970.2 -1104691.6, -735986.1 -1104673.8, -736015.7 -1104648, -736025.3 -1104638.2, -736028.3 -1104632.7, -736029.8 -1104628.9, -736050.3 -1104569.4, -736052 -1104568.1, -736053.7 -1104568.1, -736072.7 -1104570.7, -736087.1 -1104571.8, -736114.7123 -1104575.8351, -736129.1321 -1104579.1424, -736142.229 -1104582.8465, -736154.6644 -1104587.4768, -736162.0728 -1104590.9163, -736165.6447 -1104592.9007, -736169.3488 -1104595.5466, -736171.5978 -1104598.5893, -736180.701 -1104613.7, -736190.901 -1104635.2, -736192.701 -1104640.101, -736193.1 -1104644.301, -736192.301 -1104647.2, -736190.901 -1104650.2, -736187.6 -1104653.801, -736182.5 -1104656.6, -736152.1 -1104671.2, -736086.7 -1104705.3, -736032.201 -1104735.101, -736027.901 -1104738.601, -736012.8691 -1104765.9377, -735992.4 -1104797.3, -735982 -1104816.9, -735972.6 -1104835.6, -735969.1048 -1104842.7623, -735964.6683 -1104850.2215, -735957.2112 -1104860.9064, -735946.9306 -1104872.5989, -735927.7789 -1104891.9516, -735907.6197 -1104910.9001, -735900.5543 -1104918.2174, -735893.9016 -1104926.0787, -735888.4596 -1104933.3368, -735867.2 -1104964.2, -735853.8457 -1104988.5523, -735838.8808 -1105018.002, -735827.3742 -1105040.4443, -735822.744 -1105049.8371, -735814.2773 -1105069.0194, -735810.97 -1105076.6923, -735807.5304 -1105087.6725, -735805.1492 -1105097.5944, -735802.6356 -1105109.5007, -735801.0481 -1105120.7455, -735799.5929 -1105133.9747, -735798.27 -1105148.3945, -735797.7429 -1105162.2007, -735792.7523 -1105182.1632, -735793.5075 -1105191.1248, -735793.5 -1105195.9, -735790.7137 -1105208.9741, -735790.2002 -1105210.5717, -735789.2741 -1105212.5561, -735787.9512 -1105213.879, -735786.2314 -1105215.0697, -735783.1887 -1105215.9957, -735777.2356 -1105216.3926, -735754.8782 -1105215.8634, -735718.4169 -1105213.4031, -735703.5181 -1105213.4698, -735681.6087 -1105215.9466, -735666.7484 -1105218.6138, -735652.4596 -1105222.2336, -735620.2623 -1105234.9982, -735601.9488 -1105242.5864, -735578.5331 -1105250.127, -735566.4945 -1105253.0375, -735552.0747 -1105256.4771, -735543.0788 -1105259.2552, -735508.2737 -1105274.7333, -735505.7514 -1105275.6506, -735503.6876 -1105275.1919, -735501.3945 -1105273.5868, -735492.4516 -1105261.8922, -735489.9292 -1105259.8284, -735486.031 -1105258.2233, -735483.0501 -1105257.7647, -735479.3812 -1105258.4526, -735455.0747 -1105270.3765, -735432.3734 -1105283.6763, -735382.614 -1105314.174, -735340.1924 -1105338.939, -735337.4407 -1105339.6269, -735334.6891 -1105339.3976, -735332.396 -1105338.2511, -735329.6443 -1105334.5822, -735322.4319 -1105317.793, -735318.6715 -1105307.3963, -735314.358 -1105295.1194, -735308.2748 -1105273.9943, -735301.8599 -1105252.6481, -735298.763 -1105244.3529, -735295.7767 -1105238.8227, -735286.0762 -1105224.0567, -735275.5365 -1105210.6191, -735255.2962 -1105182.6366, -735224.3275 -1105147.465, -735191.3679 -1105111.0768, -735166.0399 -1105092.0531, -735110.2962 -1105061.9692, -735108.1948 -1105060.089, -735105.9827 -1105057.4345, -735104.7661 -1105055.1119, -735103.8813 -1105052.7892, -735103.5495 -1105050.5772, -735103.4389 -1105048.4757, -735103.6601 -1105046.4849, -735104.5449 -1105043.4986, -735105.4297 -1105041.1759, -735106.9782 -1105038.3003, -735109.0796 -1105034.9822, -735112.3977 -1105030.6687, -735118.9232 -1105023.4795, -735126 -1105016.1, -735143.2558 -1104998.3728, -735148.4541 -1104993.1744, -735152.657 -1104988.0867, -735157.1917 -1104981.5612, -735160.9522 -1104975.6992, -735164.9339 -1104967.7358, -735168.5838 -1104958.8876, -735178.0956 -1104931.237, -735189.9 -1104898.1, -735208.8426 -1104831.1245, -735212.5376 -1104815.3494, -735218.5066 -1104797.3004, -735223.0544 -1104787.7785, -735228.1706 -1104778.2566, -735230.4445 -1104774.8458, -735233.3741 -1104772.0031, -735235.6672 -1104770.398, -735237.7309 -1104769.2514, -735240.4826 -1104768.1049, -735244.1515 -1104767.417, -735248.9669 -1104766.9584, -735265.5477 -1104765.5955), (-735183.4045 -1105030.7793, -735183.4045 -1105024.6962, -735183.0727 -1105017.3964, -735182.2985 -1105011.2027, -735179.4489 -1105000.254, -735173.2291 -1105006.4467, -735164.1597 -1105016.5116, -735164.2703 -1105017.7282, -735173.8927 -1105026.4658, -735182.5197 -1105031.3323, -735183.4045 -1105030.7793), (-735239.5906 -1104915.642, -735222.779 -1104905.909, -735221.2306 -1104906.3514, -735211.387 -1104923.9372, -735211.8294 -1104925.0433, -735227.1445 -1104933.9846, -735228.979 -1104935.819, -735229.4376 -1104937.6535, -735223.4756 -1104972.2787, -735220.724 -1104978.47, -735217.9723 -1104981.6803, -735213.1569 -1104985.3491, -735267.961 -1104978.6993, -735248.6993 -1104947.5137, -735242.508 -1104936.7363, -735240.215 -1104930.7743, -735239.2978 -1104926.1882, -735239.7012 -1104916.4163, -735239.5906 -1104915.642), (-735250.9827 -1104830.9205, -735257.9506 -1104807.9151, -735257.5082 -1104807.1409, -735232.0696 -1104800.726, -735231.1848 -1104801.279, -735225.9865 -1104821.9617, -735226.5395 -1104822.7359, -735249.9873 -1104831.3629, -735250.9827 -1104830.9205), (-735253.8584 -1104782.2553, -735253.3255 -1104782.2359, -735247.4987 -1104786.3574, -735245.0101 -1104794.0898, -735245.2314 -1104795.4171, -735245.7844 -1104796.5231, -735247.2144 -1104797.4426, -735256.7363 -1104799.0059, -735258.2996 -1104798.5795, -735258.8681 -1104797.4426, -735259.5787 -1104787.3522, -735259.1523 -1104786.6416, -735253.8584 -1104782.2553), (-735985.949 -1104586.9388, -735980.3222 -1104587.1328, -735962.0835 -1104591.2074, -735953.7403 -1104592.5656, -735942.0986 -1104594.3118, -735939.3823 -1104595.282, -735937.83 -1104597.0282, -735937.0539 -1104600.7148, -735936.6659 -1104614.6848, -735937.636 -1104617.7892, -735939.3823 -1104618.9534, -735941.7106 -1104619.7295, -735945.2031 -1104618.5654, -735950.2478 -1104613.5206, -735959.3672 -1104601.2969, -735962.4716 -1104598.9685, -735965.5761 -1104597.8043, -735969.4566 -1104597.0282, -735990.9937 -1104594.8939, -735992.546 -1104593.9238, -735993.3221 -1104592.3716, -735993.0734 -1104590.7752, -735991.4682 -1104588.9408, -735989.0535 -1104587.5209, -735985.949 -1104586.9388))</ns2:GEOMETRIE><ns2:PLATNOSTOD>2020-04-24</ns2:PLATNOSTOD><ns2:VYMERA>39.13</ns2:VYMERA><ns2:VYMERAOPV>0</ns2:VYMERAOPV><ns2:KULTURA>T</ns2:KULTURA><ns2:KULTURAID>7</ns2:KULTURAID><ns2:KULTURANAZEV>trvalý travní porost</ns2:KULTURANAZEV><ns2:KULTURAOD>2011-04-27</ns2:KULTURAOD><ns2:UZIVATEL><ns2:IDUZIVATELE>26097</ns2:IDUZIVATELE><ns2:JMENO>ZDENĚK</ns2:JMENO><ns2:PRIJMENI>SKŘIVÁNEK</ns2:PRIJMENI><ns2:OBCHODNIJMENO>Zdeněk Skřivánek</ns2:OBCHODNIJMENO><ns2:IC>48929395</ns2:IC><ns2:PRAVNIFORMA>100</ns2:PRAVNIFORMA></ns2:UZIVATEL><ns2:ZAKLADNI><ns2:KOD>OLDIDDPB</ns2:KOD><ns2:HODNOTAINT>46355241</ns2:HODNOTAINT><ns2:PLATNOSTOD>2020-04-24</ns2:PLATNOSTOD></ns2:ZAKLADNI><ns2:ZAKLADNI><ns2:KOD>EKO</ns2:KOD><ns2:HODNOTAINT>1</ns2:HODNOTAINT><ns2:PLATNOSTOD>2020-04-24</ns2:PLATNOSTOD></ns2:ZAKLADNI><ns2:ZAKLADNI><ns2:KOD>NADMVYSKA</ns2:KOD><ns2:HODNOTANUM>603.9</ns2:HODNOTANUM><ns2:PLATNOSTOD>2016-01-01</ns2:PLATNOSTOD><ns2:PLATNOSTDO>3000-01-01</ns2:PLATNOSTDO></ns2:ZAKLADNI><ns2:ZAKLADNI><ns2:KOD>SKLONITOST</ns2:KOD><ns2:HODNOTANUM>3.08</ns2:HODNOTANUM><ns2:PLATNOSTOD>2016-01-01</ns2:PLATNOSTOD><ns2:PLATNOSTDO>3000-01-01</ns2:PLATNOSTDO></ns2:ZAKLADNI><ns2:ZAKLADNI><ns2:KOD>ORIENTS</ns2:KOD><ns2:HODNOTANUM>11</ns2:HODNOTANUM><ns2:PLATNOSTOD>2016-01-01</ns2:PLATNOSTOD><ns2:PLATNOSTDO>3000-01-01</ns2:PLATNOSTDO></ns2:ZAKLADNI><ns2:ZAKLADNI><ns2:KOD>ORIENTSV</ns2:KOD><ns2:HODNOTANUM>10</ns2:HODNOTANUM><ns2:PLATNOSTOD>2016-01-01</ns2:PLATNOSTOD><ns2:PLATNOSTDO>3000-01-01</ns2:PLATNOSTDO></ns2:ZAKLADNI><ns2:ZAKLADNI><ns2:KOD>ORIENTV</ns2:KOD><ns2:HODNOTANUM>1</ns2:HODNOTANUM><ns2:PLATNOSTOD>2016-01-01</ns2:PLATNOSTOD><ns2:PLATNOSTDO>3000-01-01</ns2:PLATNOSTDO></ns2:ZAKLADNI><ns2:ZAKLADNI><ns2:KOD>ORIENTJV</ns2:KOD><ns2:HODNOTANUM>0</ns2:HODNOTANUM><ns2:PLATNOSTOD>2016-01-01</ns2:PLATNOSTOD><ns2:PLATNOSTDO>3000-01-01</ns2:PLATNOSTDO></ns2:ZAKLADNI><ns2:ZAKLADNI><ns2:KOD>ORIENTJ</ns2:KOD><ns2:HODNOTANUM>14</ns2:HODNOTANUM><ns2:PLATNOSTOD>2016-01-01</ns2:PLATNOSTOD><ns2:PLATNOSTDO>3000-01-01</ns2:PLATNOSTDO></ns2:ZAKLADNI><ns2:ZAKLADNI><ns2:KOD>ORIENTJZ</ns2:KOD><ns2:HODNOTANUM>29</ns2:HODNOTANUM><ns2:PLATNOSTOD>2016-01-01</ns2:PLATNOSTOD><ns2:PLATNOSTDO>3000-01-01</ns2:PLATNOSTDO></ns2:ZAKLADNI><ns2:ZAKLADNI><ns2:KOD>ORIENTZ</ns2:KOD><ns2:HODNOTANUM>20</ns2:HODNOTANUM><ns2:PLATNOSTOD>2016-01-01</ns2:PLATNOSTOD><ns2:PLATNOSTDO>3000-01-01</ns2:PLATNOSTDO></ns2:ZAKLADNI><ns2:ZAKLADNI><ns2:KOD>ORIENTSZ</ns2:KOD><ns2:HODNOTANUM>8</ns2:HODNOTANUM><ns2:PLATNOSTOD>2016-01-01</ns2:PLATNOSTOD><ns2:PLATNOSTDO>3000-01-01</ns2:PLATNOSTDO></ns2:ZAKLADNI><ns2:ZAKLADNI><ns2:KOD>ORIENTR</ns2:KOD><ns2:HODNOTANUM>7</ns2:HODNOTANUM><ns2:PLATNOSTOD>2016-01-01</ns2:PLATNOSTOD><ns2:PLATNOSTDO>3000-01-01</ns2:PLATNOSTDO></ns2:ZAKLADNI><ns2:ZAKLADNI><ns2:KOD>MARGEXPOZSS</ns2:KOD><ns2:HODNOTAINT>6</ns2:HODNOTAINT><ns2:PLATNOSTOD>2016-01-01</ns2:PLATNOSTOD><ns2:PLATNOSTDO>3000-01-01</ns2:PLATNOSTDO></ns2:ZAKLADNI><ns2:ZAKLADNI><ns2:KOD>NUTS4KOD</ns2:KOD><ns2:HODNOTAINT>798428</ns2:HODNOTAINT><ns2:PLATNOSTOD>2000-04-19</ns2:PLATNOSTOD></ns2:ZAKLADNI><ns2:ZAKLADNI><ns2:KOD>OBVOD</ns2:KOD><ns2:HODNOTANUM>6443.76</ns2:HODNOTANUM><ns2:PLATNOSTOD>2020-04-24</ns2:PLATNOSTOD></ns2:ZAKLADNI><ns2:ZAKLADNI><ns2:KOD>MAPOVYLIST</ns2:KOD><ns2:HODNOTASTR>22-22-25</ns2:HODNOTASTR><ns2:PLATNOSTOD>2020-04-24</ns2:PLATNOSTOD></ns2:ZAKLADNI><ns2:ZAKLADNI><ns2:KOD>MAPOVYLIST5000</ns2:KOD><ns2:HODNOTASTR>Tabor 4-2</ns2:HODNOTASTR><ns2:PLATNOSTOD>2020-04-24</ns2:PLATNOSTOD></ns2:ZAKLADNI><ns2:ZAKLADNI><ns2:KOD>MINVZDALVODA</ns2:KOD><ns2:HODNOTANUM>2.24</ns2:HODNOTANUM><ns2:PLATNOSTOD>2020-04-24</ns2:PLATNOSTOD></ns2:ZAKLADNI><ns2:ZAKLADNI><ns2:KOD>VODAPREKRYVSVAZITE</ns2:KOD><ns2:HODNOTANUM>0.25</ns2:HODNOTANUM><ns2:PLATNOSTOD>2020-04-24</ns2:PLATNOSTOD><ns2:PLATNOSTDO>3000-01-01</ns2:PLATNOSTDO></ns2:ZAKLADNI><ns2:ZAKLADNI><ns2:KOD>VYMECP</ns2:KOD><ns2:HODNOTANUM>26.52</ns2:HODNOTANUM><ns2:PLATNOSTOD>2020-04-24</ns2:PLATNOSTOD><ns2:PLATNOSTDO>3000-01-01</ns2:PLATNOSTDO></ns2:ZAKLADNI><ns2:ZAKLADNI><ns2:KOD>VYMERAZPUS</ns2:KOD><ns2:HODNOTANUM>39.13</ns2:HODNOTANUM><ns2:PLATNOSTOD>2020-04-24</ns2:PLATNOSTOD></ns2:ZAKLADNI><ns2:ZAKLADNI><ns2:KOD>VYMERANEZPUS</ns2:KOD><ns2:HODNOTANUM>0</ns2:HODNOTANUM><ns2:PLATNOSTOD>2020-04-24</ns2:PLATNOSTOD></ns2:ZAKLADNI><ns2:PREKRYVKATUZE><ns2:KUNAZEV>Mezno</ns2:KUNAZEV><ns2:KUKOD>693839</ns2:KUKOD><ns2:VYMPREKRYV>12.51</ns2:VYMPREKRYV><ns2:DLECENTROID>0</ns2:DLECENTROID><ns2:PLATNOSTOD>2020-04-24</ns2:PLATNOSTOD><ns2:PLATNOSTDO>3000-01-01</ns2:PLATNOSTDO></ns2:PREKRYVKATUZE><ns2:PREKRYVKATUZE><ns2:KUNAZEV>Lažany u Mezna</ns2:KUNAZEV><ns2:KUKOD>693821</ns2:KUKOD><ns2:VYMPREKRYV>14.14</ns2:VYMPREKRYV><ns2:DLECENTROID>0</ns2:DLECENTROID><ns2:PLATNOSTOD>2020-04-24</ns2:PLATNOSTOD><ns2:PLATNOSTDO>3000-01-01</ns2:PLATNOSTDO></ns2:PREKRYVKATUZE><ns2:PREKRYVKATUZE><ns2:KUNAZEV>Vestec u Mezna</ns2:KUNAZEV><ns2:KUKOD>798428</ns2:KUKOD><ns2:VYMPREKRYV>12.48</ns2:VYMPREKRYV><ns2:DLECENTROID>1</ns2:DLECENTROID><ns2:PLATNOSTOD>2020-04-24</ns2:PLATNOSTOD><ns2:PLATNOSTDO>3000-01-01</ns2:PLATNOSTDO></ns2:PREKRYVKATUZE><ns2:SEZNAMEVP><ns2:EVPID>508535</ns2:EVPID><ns2:CTVEREC>730-1100</ns2:CTVEREC><ns2:ZKOD>E5403/4</ns2:ZKOD><ns2:VYMERA>864.00</ns2:VYMERA><ns2:VYMERAPREKRYV>864</ns2:VYMERAPREKRYV><ns2:GEOMETRIEEVP>POLYGON ((-735663.4592 -1104871.6178, -735666.3167 -1104871.6178, -735664.888 -1104873.6815, -735644.2504 -1104884.9528, -735631.0741 -1104890.5091, -735625.0416 -1104893.3666, -735600.7528 -1104908.4478, -735595.5141 -1104911.3054, -735590.2753 -1104913.3691, -735568.209 -1104920.1954, -735561.3828 -1104922.1004, -735559.4778 -1104922.7354, -735557.0965 -1104924.4816, -735553.604 -1104927.9741, -735551.5402 -1104929.4029, -735548.6827 -1104930.1966, -735538.999 -1104930.9904, -735533.7602 -1104930.8316, -735539.1577 -1104927.8154, -735546.7777 -1104923.2116, -735579.4803 -1104908.2891, -735616.4691 -1104891.4616, -735645.6792 -1104878.7615, -735663.4592 -1104871.6178))</ns2:GEOMETRIEEVP><ns2:DRUHNAZEV>Mez</ns2:DRUHNAZEV><ns2:DRUHID>1</ns2:DRUHID><ns2:PLATNOSTOD>2020-05-11</ns2:PLATNOSTOD></ns2:SEZNAMEVP><ns2:SEZNAMEVP><ns2:EVPID>508523</ns2:EVPID><ns2:CTVEREC>730-1100</ns2:CTVEREC><ns2:ZKOD>E5403/3</ns2:ZKOD><ns2:VYMERA>933.00</ns2:VYMERA><ns2:VYMERAPREKRYV>933</ns2:VYMERAPREKRYV><ns2:GEOMETRIEEVP>POLYGON ((-735660.368 -1104807.3724, -735663.3754 -1104807.8575, -735665.9948 -1104808.6336, -735667.256 -1104809.5067, -735668.0321 -1104810.2828, -735669.0993 -1104811.835, -735671.2336 -1104816.2977, -735673.3679 -1104822.7976, -735674.532 -1104827.2603, -735679.6738 -1104846.5661, -735679.4798 -1104847.8273, -735678.9947 -1104848.9914, -735677.8305 -1104849.8646, -735669.0022 -1104853.163, -735664.7336 -1104853.9392, -735663.7635 -1104853.6481, -735663.1814 -1104853.066, -735662.5993 -1104851.9019, -735659.2135 -1104843.1045, -735654.2923 -1104831.1982, -735651.1173 -1104825.0069, -735647.6591 -1104818.432, -735646.495 -1104815.9096, -735646.1069 -1104813.5813, -735646.495 -1104811.835, -735647.3681 -1104810.3798, -735648.4353 -1104809.5067, -735650.0845 -1104808.7306, -735655.2262 -1104807.7605, -735660.368 -1104807.3724))</ns2:GEOMETRIEEVP><ns2:DRUHNAZEV>Skupina dřevin</ns2:DRUHNAZEV><ns2:DRUHID>4</ns2:DRUHID><ns2:PLATNOSTOD>2020-05-11</ns2:PLATNOSTOD></ns2:SEZNAMEVP><ns2:LFA><ns2:LFAKOD>O3</ns2:LFAKOD><ns2:VYMPREKRYV>39.13</ns2:VYMPREKRYV><ns2:PLATNOSTOD>2020-04-24</ns2:PLATNOSTOD></ns2:LFA><ns2:VYNOSHLADINA><ns2:VYNOSHLADINAKOD>1</ns2:VYNOSHLADINAKOD><ns2:VYMPREKRYV>17.11</ns2:VYMPREKRYV><ns2:PLATNOSTOD>2020-01-01</ns2:PLATNOSTOD></ns2:VYNOSHLADINA><ns2:VYNOSHLADINA><ns2:VYNOSHLADINAKOD>2</ns2:VYNOSHLADINAKOD><ns2:VYMPREKRYV>9.49</ns2:VYMPREKRYV><ns2:PLATNOSTOD>2020-01-01</ns2:PLATNOSTOD></ns2:VYNOSHLADINA><ns2:BPEJ><ns2:BPEJKOD>00099</ns2:BPEJKOD><ns2:VYMPREKRYV>0.2</ns2:VYMPREKRYV><ns2:PLATNOSTOD>2020-04-24</ns2:PLATNOSTOD></ns2:BPEJ><ns2:BPEJ><ns2:BPEJKOD>83404</ns2:BPEJKOD><ns2:VYMPREKRYV>1.12</ns2:VYMPREKRYV><ns2:PLATNOSTOD>2020-04-24</ns2:PLATNOSTOD></ns2:BPEJ><ns2:BPEJ><ns2:BPEJKOD>83421</ns2:BPEJKOD><ns2:VYMPREKRYV>9.36</ns2:VYMPREKRYV><ns2:PLATNOSTOD>2020-04-24</ns2:PLATNOSTOD></ns2:BPEJ><ns2:BPEJ><ns2:BPEJKOD>83424</ns2:BPEJKOD><ns2:VYMPREKRYV>0.08</ns2:VYMPREKRYV><ns2:PLATNOSTOD>2020-04-24</ns2:PLATNOSTOD></ns2:BPEJ><ns2:BPEJ><ns2:BPEJKOD>85001</ns2:BPEJKOD><ns2:VYMPREKRYV>23.64</ns2:VYMPREKRYV><ns2:PLATNOSTOD>2020-04-24</ns2:PLATNOSTOD></ns2:BPEJ><ns2:BPEJ><ns2:BPEJKOD>85011</ns2:BPEJKOD><ns2:VYMPREKRYV>4.71</ns2:VYMPREKRYV><ns2:PLATNOSTOD>2020-04-24</ns2:PLATNOSTOD></ns2:BPEJ><ns2:BPEJ><ns2:BPEJKOD>86811</ns2:BPEJKOD><ns2:VYMPREKRYV>0.01</ns2:VYMPREKRYV><ns2:PLATNOSTOD>2020-04-24</ns2:PLATNOSTOD></ns2:BPEJ><ns2:OPATRENIEROZE2G><ns2:EROZOHRKOD>MEO</ns2:EROZOHRKOD><ns2:PLATNOSTOD>2020-01-01</ns2:PLATNOSTOD><ns2:PLATNOSTDO>3000-01-01</ns2:PLATNOSTDO></ns2:OPATRENIEROZE2G><ns2:OPVZ><ns2:KATEGORIEOPVZ>11</ns2:KATEGORIEOPVZ><ns2:VYMPREKRYV>0.03</ns2:VYMPREKRYV><ns2:NAZEV>Mezno   kopaná studna S1, S2</ns2:NAZEV><ns2:TYP>podzemní zdroj</ns2:TYP><ns2:OVERENO>true</ns2:OVERENO><ns2:URLROZHODNUTI>http://eagri.cz/public/app/lpisext/lpis/verejny2/evidence/rest/stahniExport?expfileid=14069209</ns2:URLROZHODNUTI><ns2:PLATNOSTOD>2020-01-01</ns2:PLATNOSTOD></ns2:OPVZ><ns2:OPVZ><ns2:KATEGORIEOPVZ>20</ns2:KATEGORIEOPVZ><ns2:VYMPREKRYV>28.4</ns2:VYMPREKRYV><ns2:NAZEV>Mezno   studny, vrt S1-4, V1</ns2:NAZEV><ns2:TYP>podzemní zdroj</ns2:TYP><ns2:OVERENO>true</ns2:OVERENO><ns2:URLROZHODNUTI>http://eagri.cz/public/app/lpisext/lpis/verejny2/evidence/rest/stahniExport?expfileid=14069215</ns2:URLROZHODNUTI><ns2:PLATNOSTOD>2020-01-01</ns2:PLATNOSTOD></ns2:OPVZ><ns2:OPVZ><ns2:KATEGORIEOPVZ>11</ns2:KATEGORIEOPVZ><ns2:VYMPREKRYV>0.04</ns2:VYMPREKRYV><ns2:NAZEV>Mezno   vrt V1</ns2:NAZEV><ns2:TYP>podzemní zdroj</ns2:TYP><ns2:OVERENO>true</ns2:OVERENO><ns2:URLROZHODNUTI>http://eagri.cz/public/app/lpisext/lpis/verejny2/evidence/rest/stahniExport?expfileid=14069252</ns2:URLROZHODNUTI><ns2:PLATNOSTOD>2020-01-01</ns2:PLATNOSTOD></ns2:OPVZ></ns2:DPB><ns2:DPB><ns2:IDDPB>12241998</ns2:IDDPB><ns2:CTVEREC>730-1100</ns2:CTVEREC><ns2:ZKOD>5404/1</ns2:ZKOD><ns2:STAV>UCINNY</ns2:STAV><ns2:STAVID>4</ns2:STAVID><ns2:UCINNOST_DLE_ZAKONA>2020-05-11</ns2:UCINNOST_DLE_ZAKONA><ns2:GEOMETRIE>POLYGON ((-735542.6885 -1104453.1047, -735551.6461 -1104448.8713, -735559.7424 -1104445.0613, -735572.4424 -1104439.3462, -735598.0012 -1104428.2337, -735634.7 -1104413.3, -735660.2349 -1104402.9748, -735667.1141 -1104400.3289, -735670.9946 -1104398.3887, -735678.1701 -1104394.4199, -735680.2339 -1104393.4674, -735681.5613 -1104393.283, -735682.6902 -1104393.7769, -735683.39 -1104394.4457, -735684.1013 -1104395.4702, -735684.8818 -1104397.3091, -735685.6755 -1104400.6429, -735685.9118 -1104403.0398, -735685.9118 -1104404.3098, -735685.3826 -1104405.3681, -735684.0068 -1104406.6381, -735668.7668 -1104415.9514, -735667.7084 -1104417.2214, -735667.1793 -1104418.7031, -735667.1793 -1104420.2906, -735667.4968 -1104421.7723, -735668.5551 -1104423.254, -735669.9309 -1104423.889, -735671.5184 -1104424.2065, -735672.8943 -1104423.7831, -735677.1276 -1104421.1373, -735679.9851 -1104419.5498, -735681.7843 -1104418.9148, -735684.3243 -1104418.7031, -735686.8643 -1104419.0206, -735690.3568 -1104420.1848, -735695.5218 -1104422.0403, -735698.1412 -1104422.5254, -735705.5143 -1104422.8164, -735712.606 -1104422.6746, -735717.7213 -1104421.9691, -735723.451 -1104420.6121, -735723.5936 -1104420.6406, -735724.6519 -1104421.0639, -735725.2869 -1104421.8047, -735725.4986 -1104422.6514, -735725.5689 -1104423.4633, -735725.1808 -1104424.4334, -735724.2107 -1104426.2767, -735722.3674 -1104428.9931, -735711.8556 -1104444.0463, -735694.0756 -1104464.2075, -735686.6143 -1104471.5101, -735678.0418 -1104480.2413, -735657.2455 -1104505.0064, -735653.9117 -1104509.2926, -735639.6242 -1104531.2002, -735635.4967 -1104536.4389, -735633.2742 -1104538.5027, -735631.0517 -1104540.0902, -735628.8292 -1104540.8839, -735626.7654 -1104541.3602, -735624.4802 -1104541.3354, -735622.1519 -1104541.0444, -735619.4355 -1104540.3653, -735614.2937 -1104538.522, -735612.3534 -1104537.6489, -735609.443 -1104535.9996, -735607.591 -1104534.4324, -735605.3097 -1104532.6074, -735603.3706 -1104530.4402, -735601.3 -1104527.5, -735596.2491 -1104518.1491, -735593.4357 -1104513.2013, -735587.9059 -1104505.1492, -735581.1149 -1104495.9328, -735577.1373 -1104491.2761, -735571.9966 -1104485.3213, -735565.3986 -1104478.9554, -735555.6886 -1104470.2892, -735546.9 -1104464.6, -735541.89 -1104461.8876, -735540.6353 -1104460.747, -735539.7228 -1104459.2641, -735539.3806 -1104457.5532, -735539.4947 -1104456.0703, -735540.2931 -1104454.7016, -735542.6885 -1104453.1047))</ns2:GEOMETRIE><ns2:PLATNOSTOD>2020-05-11</ns2:PLATNOSTOD><ns2:VYMERA>1.29</ns2:VYMERA><ns2:VYMERAOPV>0</ns2:VYMERAOPV><ns2:KULTURA>T</ns2:KULTURA><ns2:KULTURAID>7</ns2:KULTURAID><ns2:KULTURANAZEV>trvalý travní porost</ns2:KULTURANAZEV><ns2:KULTURAOD>2004-04-29</ns2:KULTURAOD><ns2:UZIVATEL><ns2:IDUZIVATELE>26097</ns2:IDUZIVATELE><ns2:JMENO>ZDENĚK</ns2:JMENO><ns2:PRIJMENI>SKŘIVÁNEK</ns2:PRIJMENI><ns2:OBCHODNIJMENO>Zdeněk Skřivánek</ns2:OBCHODNIJMENO><ns2:IC>48929395</ns2:IC><ns2:PRAVNIFORMA>100</ns2:PRAVNIFORMA></ns2:UZIVATEL><ns2:ZAKLADNI><ns2:KOD>OLDIDDPB</ns2:KOD><ns2:HODNOTAINT>46432898</ns2:HODNOTAINT><ns2:PLATNOSTOD>2020-05-11</ns2:PLATNOSTOD></ns2:ZAKLADNI><ns2:ZAKLADNI><ns2:KOD>EKO</ns2:KOD><ns2:HODNOTAINT>1</ns2:HODNOTAINT><ns2:PLATNOSTOD>2020-05-11</ns2:PLATNOSTOD></ns2:ZAKLADNI><ns2:ZAKLADNI><ns2:KOD>NADMVYSKA</ns2:KOD><ns2:HODNOTANUM>606.85</ns2:HODNOTANUM><ns2:PLATNOSTOD>2016-01-01</ns2:PLATNOSTOD><ns2:PLATNOSTDO>3000-01-01</ns2:PLATNOSTDO></ns2:ZAKLADNI><ns2:ZAKLADNI><ns2:KOD>SKLONITOST</ns2:KOD><ns2:HODNOTANUM>4.28</ns2:HODNOTANUM><ns2:PLATNOSTOD>2016-01-01</ns2:PLATNOSTOD><ns2:PLATNOSTDO>3000-01-01</ns2:PLATNOSTDO></ns2:ZAKLADNI><ns2:ZAKLADNI><ns2:KOD>ORIENTS</ns2:KOD><ns2:HODNOTANUM>0</ns2:HODNOTANUM><ns2:PLATNOSTOD>2016-01-01</ns2:PLATNOSTOD><ns2:PLATNOSTDO>3000-01-01</ns2:PLATNOSTDO></ns2:ZAKLADNI><ns2:ZAKLADNI><ns2:KOD>ORIENTSV</ns2:KOD><ns2:HODNOTANUM>0</ns2:HODNOTANUM><ns2:PLATNOSTOD>2016-01-01</ns2:PLATNOSTOD><ns2:PLATNOSTDO>3000-01-01</ns2:PLATNOSTDO></ns2:ZAKLADNI><ns2:ZAKLADNI><ns2:KOD>ORIENTV</ns2:KOD><ns2:HODNOTANUM>0</ns2:HODNOTANUM><ns2:PLATNOSTOD>2016-01-01</ns2:PLATNOSTOD><ns2:PLATNOSTDO>3000-01-01</ns2:PLATNOSTDO></ns2:ZAKLADNI><ns2:ZAKLADNI><ns2:KOD>ORIENTJV</ns2:KOD><ns2:HODNOTANUM>0</ns2:HODNOTANUM><ns2:PLATNOSTOD>2016-01-01</ns2:PLATNOSTOD><ns2:PLATNOSTDO>3000-01-01</ns2:PLATNOSTDO></ns2:ZAKLADNI><ns2:ZAKLADNI><ns2:KOD>ORIENTJ</ns2:KOD><ns2:HODNOTANUM>0</ns2:HODNOTANUM><ns2:PLATNOSTOD>2016-01-01</ns2:PLATNOSTOD><ns2:PLATNOSTDO>3000-01-01</ns2:PLATNOSTDO></ns2:ZAKLADNI><ns2:ZAKLADNI><ns2:KOD>ORIENTJZ</ns2:KOD><ns2:HODNOTANUM>44</ns2:HODNOTANUM><ns2:PLATNOSTOD>2016-01-01</ns2:PLATNOSTOD><ns2:PLATNOSTDO>3000-01-01</ns2:PLATNOSTDO></ns2:ZAKLADNI><ns2:ZAKLADNI><ns2:KOD>ORIENTZ</ns2:KOD><ns2:HODNOTANUM>53</ns2:HODNOTANUM><ns2:PLATNOSTOD>2016-01-01</ns2:PLATNOSTOD><ns2:PLATNOSTDO>3000-01-01</ns2:PLATNOSTDO></ns2:ZAKLADNI><ns2:ZAKLADNI><ns2:KOD>ORIENTSZ</ns2:KOD><ns2:HODNOTANUM>2</ns2:HODNOTANUM><ns2:PLATNOSTOD>2016-01-01</ns2:PLATNOSTOD><ns2:PLATNOSTDO>3000-01-01</ns2:PLATNOSTDO></ns2:ZAKLADNI><ns2:ZAKLADNI><ns2:KOD>ORIENTR</ns2:KOD><ns2:HODNOTANUM>0</ns2:HODNOTANUM><ns2:PLATNOSTOD>2016-01-01</ns2:PLATNOSTOD><ns2:PLATNOSTDO>3000-01-01</ns2:PLATNOSTDO></ns2:ZAKLADNI><ns2:ZAKLADNI><ns2:KOD>MARGEXPOZSS</ns2:KOD><ns2:HODNOTAINT>5</ns2:HODNOTAINT><ns2:PLATNOSTOD>2016-01-01</ns2:PLATNOSTOD><ns2:PLATNOSTDO>3000-01-01</ns2:PLATNOSTDO></ns2:ZAKLADNI><ns2:ZAKLADNI><ns2:KOD>NUTS4KOD</ns2:KOD><ns2:HODNOTAINT>798428</ns2:HODNOTAINT><ns2:PLATNOSTOD>2000-04-19</ns2:PLATNOSTOD></ns2:ZAKLADNI><ns2:ZAKLADNI><ns2:KOD>OBVOD</ns2:KOD><ns2:HODNOTANUM>540.5</ns2:HODNOTANUM><ns2:PLATNOSTOD>2020-05-11</ns2:PLATNOSTOD></ns2:ZAKLADNI><ns2:ZAKLADNI><ns2:KOD>MAPOVYLIST</ns2:KOD><ns2:HODNOTASTR>22-22-25</ns2:HODNOTASTR><ns2:PLATNOSTOD>2020-05-11</ns2:PLATNOSTOD></ns2:ZAKLADNI><ns2:ZAKLADNI><ns2:KOD>MAPOVYLIST5000</ns2:KOD><ns2:HODNOTASTR>Tabor 4-2</ns2:HODNOTASTR><ns2:PLATNOSTOD>2020-05-11</ns2:PLATNOSTOD></ns2:ZAKLADNI><ns2:ZAKLADNI><ns2:KOD>MINVZDALVODA</ns2:KOD><ns2:HODNOTANUM>56.37</ns2:HODNOTANUM><ns2:PLATNOSTOD>2020-05-11</ns2:PLATNOSTOD></ns2:ZAKLADNI><ns2:ZAKLADNI><ns2:KOD>VODAPREKRYVSVAZITE</ns2:KOD><ns2:HODNOTANUM>0.27</ns2:HODNOTANUM><ns2:PLATNOSTOD>2020-05-11</ns2:PLATNOSTOD><ns2:PLATNOSTDO>3000-01-01</ns2:PLATNOSTDO></ns2:ZAKLADNI><ns2:ZAKLADNI><ns2:KOD>VYMECP</ns2:KOD><ns2:HODNOTANUM>1.29</ns2:HODNOTANUM><ns2:PLATNOSTOD>2020-05-11</ns2:PLATNOSTOD><ns2:PLATNOSTDO>3000-01-01</ns2:PLATNOSTDO></ns2:ZAKLADNI><ns2:ZAKLADNI><ns2:KOD>VYMERAZPUS</ns2:KOD><ns2:HODNOTANUM>1.29</ns2:HODNOTANUM><ns2:PLATNOSTOD>2020-05-11</ns2:PLATNOSTOD></ns2:ZAKLADNI><ns2:ZAKLADNI><ns2:KOD>VYMERANEZPUS</ns2:KOD><ns2:HODNOTANUM>0</ns2:HODNOTANUM><ns2:PLATNOSTOD>2020-05-11</ns2:PLATNOSTOD></ns2:ZAKLADNI><ns2:PREKRYVKATUZE><ns2:KUNAZEV>Lažany u Mezna</ns2:KUNAZEV><ns2:KUKOD>693821</ns2:KUKOD><ns2:VYMPREKRYV>0.44</ns2:VYMPREKRYV><ns2:DLECENTROID>0</ns2:DLECENTROID><ns2:PLATNOSTOD>2020-05-11</ns2:PLATNOSTOD><ns2:PLATNOSTDO>3000-01-01</ns2:PLATNOSTDO></ns2:PREKRYVKATUZE><ns2:PREKRYVKATUZE><ns2:KUNAZEV>Vestec u Mezna</ns2:KUNAZEV><ns2:KUKOD>798428</ns2:KUKOD><ns2:VYMPREKRYV>0.85</ns2:VYMPREKRYV><ns2:DLECENTROID>1</ns2:DLECENTROID><ns2:PLATNOSTOD>2020-05-11</ns2:PLATNOSTOD><ns2:PLATNOSTDO>3000-01-01</ns2:PLATNOSTDO></ns2:PREKRYVKATUZE><ns2:LFA><ns2:LFAKOD>O3</ns2:LFAKOD><ns2:VYMPREKRYV>1.29</ns2:VYMPREKRYV><ns2:PLATNOSTOD>2020-05-11</ns2:PLATNOSTOD></ns2:LFA><ns2:VYNOSHLADINA><ns2:VYNOSHLADINAKOD>1</ns2:VYNOSHLADINAKOD><ns2:VYMPREKRYV>0.69</ns2:VYMPREKRYV><ns2:PLATNOSTOD>2020-01-01</ns2:PLATNOSTOD></ns2:VYNOSHLADINA><ns2:VYNOSHLADINA><ns2:VYNOSHLADINAKOD>2</ns2:VYNOSHLADINAKOD><ns2:VYMPREKRYV>0.59</ns2:VYMPREKRYV><ns2:PLATNOSTOD>2020-01-01</ns2:PLATNOSTOD></ns2:VYNOSHLADINA><ns2:BPEJ><ns2:BPEJKOD>83421</ns2:BPEJKOD><ns2:VYMPREKRYV>0.59</ns2:VYMPREKRYV><ns2:PLATNOSTOD>2020-05-11</ns2:PLATNOSTOD></ns2:BPEJ><ns2:BPEJ><ns2:BPEJKOD>85011</ns2:BPEJKOD><ns2:VYMPREKRYV>0.69</ns2:VYMPREKRYV><ns2:PLATNOSTOD>2020-05-11</ns2:PLATNOSTOD></ns2:BPEJ><ns2:OPATRENIEROZE2G><ns2:EROZOHRKOD>NEO</ns2:EROZOHRKOD><ns2:PLATNOSTOD>2020-01-01</ns2:PLATNOSTOD><ns2:PLATNOSTDO>3000-01-01</ns2:PLATNOSTDO></ns2:OPATRENIEROZE2G></ns2:DPB><ns2:DPB><ns2:IDDPB>12242010</ns2:IDDPB><ns2:CTVEREC>730-1100</ns2:CTVEREC><ns2:ZKOD>6403/3</ns2:ZKOD><ns2:STAV>UCINNY</ns2:STAV><ns2:STAVID>4</ns2:STAVID><ns2:UCINNOST_DLE_ZAKONA>2020-05-11</ns2:UCINNOST_DLE_ZAKONA><ns2:GEOMETRIE>POLYGON ((-736319.7965 -1104540.3487, -736308.3064 -1104530.0193, -736306.7976 -1104529.3229, -736304.1282 -1104528.7426, -736301.5748 -1104528.6266, -736283.9335 -1104527.582, -736237.7 -1104527.5, -736234.9 -1104528.4, -736233.4468 -1104529.3229, -736231.4737 -1104531.1799, -736227.8758 -1104536.983, -736225.4027 -1104541.0423, -736222.2983 -1104543.8645, -736212.7027 -1104548.6623, -736207.6227 -1104552.049, -736203.6715 -1104554.8712, -736198.8738 -1104558.5401, -736195.4871 -1104562.4912, -736194.2171 -1104565.1723, -736194.3582 -1104568.559, -736194.9226 -1104572.5101, -736198.8605 -1104586.4251, -736198.7444 -1104588.5142, -736197.6999 -1104590.2551, -736195.8429 -1104591.9961, -736187.6025 -1104597.567, -736186.0937 -1104597.9152, -736184.4689 -1104597.6831, -736182.844 -1104597.1028, -736174.8358 -1104593.2727, -736141.0516 -1104578.2163, -736135.2308 -1104576.276, -736130.3801 -1104574.9178, -736121.2607 -1104573.3656, -736088.47 -1104565.6045, -736073.6497 -1104563.2673, -736071.1274 -1104562.1032, -736068.799 -1104559.9689, -736067.6349 -1104557.2525, -736067.6349 -1104554.7301, -736069.1871 -1104552.2077, -736071.3214 -1104550.6555, -736075.202 -1104549.2973, -736085.2914 -1104546.3869, -736096.157 -1104543.8645, -736103.9181 -1104542.7003, -736111.6793 -1104542.3123, -736121.1866 -1104542.3123, -736132.8283 -1104543.2824, -736135.1567 -1104542.7003, -736135.7388 -1104540.9541, -736135.5447 -1104538.6258, -736134.0982 -1104536.4027, -736132.7055 -1104534.7778, -736130.4413 -1104533.9396, -736127.478 -1104533.1987, -736108.4632 -1104532.4579, -736093.6465 -1104531.4701, -736084.0157 -1104529.9885, -736076.3604 -1104527.519, -736069.4459 -1104523.8148, -736041.7881 -1104506.2817, -736024.1881 -1104492.6475, -736018.2899 -1104489.1236, -736016.8083 -1104489.8644, -736016.5613 -1104491.3461, -736017.5063 -1104493.166, -736027.6738 -1104504.928, -736028.9086 -1104507.3975, -736029.4408 -1104511.7145, -736028.9469 -1104515.6656, -736026.2305 -1104524.5557, -736024.9958 -1104530.7293, -736025.4897 -1104538.8785, -736025.4897 -1104543.3235, -736024.5019 -1104546.2868, -736022.5264 -1104549.2502, -736020.0569 -1104551.2257, -736015.8589 -1104553.2013, -736011.6608 -1104553.9421, -736008.1368 -1104553.6065, -735990.702 -1104551.301, -735980.1 -1104550.4, -735949.264 -1104544.98, -735888.833 -1104533.663, -735816.1 -1104522.7, -735801.4 -1104521.6, -735790.5 -1104520.5, -735783.3 -1104519.1, -735771.6 -1104516.5, -735754.2424 -1104514.6798, -735750.0443 -1104513.445, -735747.3279 -1104511.9634, -735746.3401 -1104509, -735750.5154 -1104486.3802, -735750.9796 -1104484.8714, -735750.6315 -1104483.4787, -735747.846 -1104477.9077, -735747.4978 -1104476.2829, -735747.5 -1104475, -735754.3 -1104448.6, -735756.6 -1104437.1, -735756.3 -1104435.6, -735755.301 -1104434.4, -735747.2657 -1104425.9122, -735746.4533 -1104424.7516, -735745.9937 -1104423.3729, -735745.8729 -1104421.8501, -735746.5693 -1104419.9931, -735747.7299 -1104418.0201, -735749.3548 -1104415.6988, -735753.3837 -1104411.8165, -735755.7382 -1104409.5476, -735794.3 -1104377, -735822.5 -1104345.5, -735835.5 -1104332.1, -735848.602 -1104320.088, -735856.9437 -1104311.2436, -735867.2731 -1104299.1732, -735886.6554 -1104276.4252, -735913.0013 -1104247.758, -735922.1702 -1104238.241, -735932.3594 -1104226.2263, -735947.2152 -1104208.8171, -735955.9198 -1104197.0949, -735964.8566 -1104184.4442, -735968.2224 -1104179.6857, -735969.9633 -1104177.5966, -735974.5172 -1104173.1549, -735979.95 -1104167.4752, -735984.395 -1104161.3016, -735996.0949 -1104150.2784, -736015.1097 -1104139.6597, -736019.0608 -1104138.1781, -736023.7528 -1104137.6842, -736026.8696 -1104137.5948, -736031.3146 -1104136.3601, -736036.9943 -1104133.1498, -736062.5231 -1104111.0141, -736069.4376 -1104102.618, -736078.0806 -1104091.5055, -736079.0684 -1104088.7891, -736078.3276 -1104084.838, -736073.8826 -1104075.2071, -736068.6967 -1104068.2927, -736063.2639 -1104064.0946, -736060.3006 -1104063.1068, -736057.5842 -1104063.3538, -736053.1392 -1104064.5885, -736012.5062 -1104087.766, -736011.342 -1104087.9601, -736009.9838 -1104086.9899, -735971.1782 -1104043.1396, -735970.5961 -1104041.7814, -735970.7901 -1104040.4232, -735973.4451 -1104036.3499, -735987.8367 -1104021.7262, -736010.3526 -1103997.3533, -736024.7442 -1103982.1493, -736038.5556 -1103967.8737, -736055.8487 -1103950.8127, -736058.1699 -1103949.1878, -736060.143 -1103948.0272, -736062.8124 -1103946.9827, -736072.9097 -1103943.9651, -736097.5147 -1103937.2335, -736115.04 -1103934.2159, -736120.3788 -1103933.5195, -736134.0741 -1103932.0107, -736161.4645 -1103928.0647, -736164.8303 -1103928.2968, -736166.9194 -1103928.645, -736170.6334 -1103929.6895, -736174.9277 -1103931.7786, -736177.9453 -1103933.0553, -736182.0074 -1103933.8677, -736186.4177 -1103934.332, -736191.0602 -1103934.5641, -736236.4402 -1103935.3765, -736284.8378 -1103933.8677, -736290.989 -1103934.2159, -736296.2118 -1103934.7962, -736299.8097 -1103935.6086, -736302.5952 -1103936.6532, -736305.2646 -1103938.0459, -736309.2107 -1103940.4832, -736322.6738 -1103951.509, -736327.8954 -1103957.0781, -736330.8588 -1103961.0292, -736332.5874 -1103964.7334, -736335.7977 -1103985.9706, -736338.0202 -1103990.1687, -736351.2249 -1104006.0579, -736359.5813 -1104018.1283, -736369.701 -1104035.9, -736379.2 -1104061.5, -736384 -1104077.1, -736386.7 -1104090.1, -736389.0807 -1104110.9336, -736389.3 -1104117.1, -736389.5 -1104120.8, -736388.9 -1104125.5, -736387.7 -1104129.9, -736376.884 -1104152.976, -736369.6 -1104169.3, -736366.7 -1104178.5, -736365.8 -1104181.6, -736365.2 -1104186.4, -736364.8 -1104198.5, -736364.4 -1104208, -736363.6 -1104210.8, -736362.1 -1104213.5, -736354.401 -1104221.301, -736317.6 -1104255, -736308.301 -1104263.7, -736290.3 -1104279.6, -736288.3 -1104282.2, -736287.6 -1104285.4, -736288 -1104288, -736288.7 -1104290.2, -736289.4 -1104292.2, -736290.9 -1104293.7, -736293.6 -1104295.1, -736295.4 -1104295, -736297.4 -1104294.2, -736317 -1104279.301, -736340.5 -1104266.7, -736356.9 -1104260.5, -736362.1 -1104259.2, -736367.9 -1104258.8, -736373 -1104259.5, -736378.1 -1104261.7, -736380.2478 -1104264.5245, -736381.4825 -1104266.994, -736382.7172 -1104284.774, -736384.6928 -1104314.1605, -736386.7 -1104320.4, -736387.4755 -1104323.271, -736389.5393 -1104326.252, -736391.3737 -1104328.545, -736438.9673 -1104360.7415, -736446.7434 -1104367.1248, -736448.3683 -1104367.8212, -736450.9933 -1104368.215, -736453.5157 -1104367.0684, -736454.8915 -1104365.234, -736460.8535 -1104349.4119, -736467.7327 -1104329.4622, -736477.4997 -1104302.3626, -736478.4282 -1104301.4341, -736479.5888 -1104300.9699, -736480.8655 -1104301.0859, -736486.9 -1104302.9, -736568.0276 -1104324.4143, -736571.1612 -1104325.5749, -736572.5539 -1104326.3873, -736574.5893 -1104328.545, -736576.1944 -1104331.7553, -736576.653 -1104334.2777, -736576.8823 -1104336.5707, -736576.4237 -1104339.5517, -736574.3599 -1104344.5964, -736537.4417 -1104398.0247, -736495.7186 -1104451.162, -736478.5684 -1104474.1938, -736459 -1104500.2, -736446.8658 -1104517.2639, -736442.0504 -1104522.0793, -736437.9229 -1104525.2896, -736434.0247 -1104527.3533, -736428.0627 -1104529.8757, -736419.5784 -1104532.8567, -736405.82 -1104536.5256, -736393.8961 -1104539.2772, -736381.9722 -1104540.8824, -736368.4431 -1104542.2582, -736323.8586 -1104541.8575, -736321.5374 -1104541.3933, -736319.7965 -1104540.3487), (-735866.6928 -1104378.6753, -735862.3986 -1104380.068, -735859.6878 -1104382.0703, -735856.2306 -1104384.2928, -735852.7734 -1104387.997, -735847.0937 -1104395.1584, -735829.3211 -1104418.3682, -735821.6157 -1104430.4369, -735819.6 -1104433.2, -735819.4559 -1104434.7329, -735820.0362 -1104436.1256, -735821.1968 -1104437.4023, -735827.7 -1104442.8, -735832.1 -1104446.301, -735835.301 -1104449.7, -735838.8 -1104452.4, -735842.0878 -1104453.5348, -735844.6412 -1104454.1151, -735847.3106 -1104454.2312, -735851.2567 -1104454.1151, -735854.3903 -1104453.4188, -735856.8276 -1104452.4903, -735859.6131 -1104450.6333, -735862.8628 -1104447.7318, -735875.2814 -1104433.6883, -735885.2882 -1104419.1159, -735893.8512 -1104406.646, -735895.36 -1104403.1642, -735896.4046 -1104399.6824, -735896.9849 -1104397.129, -735896.9849 -1104394.8078, -735896.8688 -1104392.7187, -735896.2885 -1104390.8617, -735895.6608 -1104390.2041, -735895.6 -1104389.9, -735894.4598 -1104388.9459, -735893.8512 -1104388.3083, -735890.3694 -1104385.5229, -735877.6 -1104378.6, -735875.1653 -1104377.8628, -735872.612 -1104377.7468, -735869.8265 -1104378.0949, -735866.6928 -1104378.6753), (-736148.9541 -1104563.561, -736146.6379 -1104569.2546, -736152.7841 -1104571.6853, -736155.3375 -1104566.2304, -736148.9541 -1104563.561), (-736349.7 -1104178.9, -736347.6 -1104180.7, -736346.2 -1104183.5, -736345.8 -1104188.3, -736346.2 -1104193, -736347 -1104195.7, -736349.736 -1104202.695, -736351.5 -1104204.3, -736353.2 -1104204.9, -736355.1 -1104204.5, -736356.6 -1104202.8, -736357.68 -1104196.806, -736358.23 -1104186.948, -736357 -1104182.2, -736354.5 -1104179.4, -736351.9 -1104178.6, -736349.7 -1104178.9), (-735900.2909 -1104283.8976, -735898.1742 -1104283.1921, -735896.0575 -1104283.5449, -735893.7645 -1104284.4268, -735889.7075 -1104287.6018, -735887.2381 -1104290.2477, -735885.2978 -1104293.2463, -735884.2394 -1104296.2449, -735884.5922 -1104298.3616, -735885.827 -1104300.1254, -735887.7672 -1104301.8893, -735890.2367 -1104303.3005, -735893.5881 -1104304.1824, -735896.9395 -1104304.006, -735899.5853 -1104302.4185, -735902.0548 -1104299.0671, -735903.2895 -1104296.4213, -735903.8187 -1104292.7171, -735903.6423 -1104289.7185, -735902.7603 -1104287.249, -735901.702 -1104285.3088, -735900.2909 -1104283.8976))</ns2:GEOMETRIE><ns2:PLATNOSTOD>2020-05-11</ns2:PLATNOSTOD><ns2:VYMERA>30.38</ns2:VYMERA><ns2:VYMERAOPV>0</ns2:VYMERAOPV><ns2:KULTURA>T</ns2:KULTURA><ns2:KULTURAID>7</ns2:KULTURAID><ns2:KULTURANAZEV>trvalý travní porost</ns2:KULTURANAZEV><ns2:KULTURAOD>2005-01-01</ns2:KULTURAOD><ns2:UZIVATEL><ns2:IDUZIVATELE>26097</ns2:IDUZIVATELE><ns2:JMENO>ZDENĚK</ns2:JMENO><ns2:PRIJMENI>SKŘIVÁNEK</ns2:PRIJMENI><ns2:OBCHODNIJMENO>Zdeněk Skřivánek</ns2:OBCHODNIJMENO><ns2:IC>48929395</ns2:IC><ns2:PRAVNIFORMA>100</ns2:PRAVNIFORMA></ns2:UZIVATEL><ns2:ZAKLADNI><ns2:KOD>OLDIDDPB</ns2:KOD><ns2:HODNOTAINT>46432900</ns2:HODNOTAINT><ns2:PLATNOSTOD>2020-05-11</ns2:PLATNOSTOD></ns2:ZAKLADNI><ns2:ZAKLADNI><ns2:KOD>EKO</ns2:KOD><ns2:HODNOTAINT>1</ns2:HODNOTAINT><ns2:PLATNOSTOD>2020-05-11</ns2:PLATNOSTOD></ns2:ZAKLADNI><ns2:ZAKLADNI><ns2:KOD>NADMVYSKA</ns2:KOD><ns2:HODNOTANUM>587.13</ns2:HODNOTANUM><ns2:PLATNOSTOD>2016-01-01</ns2:PLATNOSTOD><ns2:PLATNOSTDO>3000-01-01</ns2:PLATNOSTDO></ns2:ZAKLADNI><ns2:ZAKLADNI><ns2:KOD>SKLONITOST</ns2:KOD><ns2:HODNOTANUM>4.98</ns2:HODNOTANUM><ns2:PLATNOSTOD>2016-01-01</ns2:PLATNOSTOD><ns2:PLATNOSTDO>3000-01-01</ns2:PLATNOSTDO></ns2:ZAKLADNI><ns2:ZAKLADNI><ns2:KOD>ORIENTS</ns2:KOD><ns2:HODNOTANUM>5</ns2:HODNOTANUM><ns2:PLATNOSTOD>2016-01-01</ns2:PLATNOSTOD><ns2:PLATNOSTDO>3000-01-01</ns2:PLATNOSTDO></ns2:ZAKLADNI><ns2:ZAKLADNI><ns2:KOD>ORIENTSV</ns2:KOD><ns2:HODNOTANUM>1</ns2:HODNOTANUM><ns2:PLATNOSTOD>2016-01-01</ns2:PLATNOSTOD><ns2:PLATNOSTDO>3000-01-01</ns2:PLATNOSTDO></ns2:ZAKLADNI><ns2:ZAKLADNI><ns2:KOD>ORIENTV</ns2:KOD><ns2:HODNOTANUM>0</ns2:HODNOTANUM><ns2:PLATNOSTOD>2016-01-01</ns2:PLATNOSTOD><ns2:PLATNOSTDO>3000-01-01</ns2:PLATNOSTDO></ns2:ZAKLADNI><ns2:ZAKLADNI><ns2:KOD>ORIENTJV</ns2:KOD><ns2:HODNOTANUM>1</ns2:HODNOTANUM><ns2:PLATNOSTOD>2016-01-01</ns2:PLATNOSTOD><ns2:PLATNOSTDO>3000-01-01</ns2:PLATNOSTDO></ns2:ZAKLADNI><ns2:ZAKLADNI><ns2:KOD>ORIENTJ</ns2:KOD><ns2:HODNOTANUM>30</ns2:HODNOTANUM><ns2:PLATNOSTOD>2016-01-01</ns2:PLATNOSTOD><ns2:PLATNOSTDO>3000-01-01</ns2:PLATNOSTDO></ns2:ZAKLADNI><ns2:ZAKLADNI><ns2:KOD>ORIENTJZ</ns2:KOD><ns2:HODNOTANUM>33</ns2:HODNOTANUM><ns2:PLATNOSTOD>2016-01-01</ns2:PLATNOSTOD><ns2:PLATNOSTDO>3000-01-01</ns2:PLATNOSTDO></ns2:ZAKLADNI><ns2:ZAKLADNI><ns2:KOD>ORIENTZ</ns2:KOD><ns2:HODNOTANUM>16</ns2:HODNOTANUM><ns2:PLATNOSTOD>2016-01-01</ns2:PLATNOSTOD><ns2:PLATNOSTDO>3000-01-01</ns2:PLATNOSTDO></ns2:ZAKLADNI><ns2:ZAKLADNI><ns2:KOD>ORIENTSZ</ns2:KOD><ns2:HODNOTANUM>13</ns2:HODNOTANUM><ns2:PLATNOSTOD>2016-01-01</ns2:PLATNOSTOD><ns2:PLATNOSTDO>3000-01-01</ns2:PLATNOSTDO></ns2:ZAKLADNI><ns2:ZAKLADNI><ns2:KOD>ORIENTR</ns2:KOD><ns2:HODNOTANUM>0</ns2:HODNOTANUM><ns2:PLATNOSTOD>2016-01-01</ns2:PLATNOSTOD><ns2:PLATNOSTDO>3000-01-01</ns2:PLATNOSTDO></ns2:ZAKLADNI><ns2:ZAKLADNI><ns2:KOD>MARGEXPOZSS</ns2:KOD><ns2:HODNOTAINT>6</ns2:HODNOTAINT><ns2:PLATNOSTOD>2016-01-01</ns2:PLATNOSTOD><ns2:PLATNOSTDO>3000-01-01</ns2:PLATNOSTDO></ns2:ZAKLADNI><ns2:ZAKLADNI><ns2:KOD>NUTS4KOD</ns2:KOD><ns2:HODNOTAINT>798428</ns2:HODNOTAINT><ns2:PLATNOSTOD>2000-04-19</ns2:PLATNOSTOD></ns2:ZAKLADNI><ns2:ZAKLADNI><ns2:KOD>OBVOD</ns2:KOD><ns2:HODNOTANUM>3550.05</ns2:HODNOTANUM><ns2:PLATNOSTOD>2020-05-11</ns2:PLATNOSTOD></ns2:ZAKLADNI><ns2:ZAKLADNI><ns2:KOD>MAPOVYLIST</ns2:KOD><ns2:HODNOTASTR>22-22-25</ns2:HODNOTASTR><ns2:PLATNOSTOD>2020-05-11</ns2:PLATNOSTOD></ns2:ZAKLADNI><ns2:ZAKLADNI><ns2:KOD>MAPOVYLIST5000</ns2:KOD><ns2:HODNOTASTR>Tabor 4-2</ns2:HODNOTASTR><ns2:PLATNOSTOD>2020-05-11</ns2:PLATNOSTOD></ns2:ZAKLADNI><ns2:ZAKLADNI><ns2:KOD>MINVZDALVODA</ns2:KOD><ns2:HODNOTANUM>0</ns2:HODNOTANUM><ns2:PLATNOSTOD>2020-05-11</ns2:PLATNOSTOD></ns2:ZAKLADNI><ns2:ZAKLADNI><ns2:KOD>VODAPREKRYVSVAZITE</ns2:KOD><ns2:HODNOTANUM>2.1</ns2:HODNOTANUM><ns2:PLATNOSTOD>2020-05-11</ns2:PLATNOSTOD><ns2:PLATNOSTDO>3000-01-01</ns2:PLATNOSTDO></ns2:ZAKLADNI><ns2:ZAKLADNI><ns2:KOD>VYMECP</ns2:KOD><ns2:HODNOTANUM>30.21</ns2:HODNOTANUM><ns2:PLATNOSTOD>2020-05-11</ns2:PLATNOSTOD><ns2:PLATNOSTDO>3000-01-01</ns2:PLATNOSTDO></ns2:ZAKLADNI><ns2:ZAKLADNI><ns2:KOD>VYMERAZPUS</ns2:KOD><ns2:HODNOTANUM>30.38</ns2:HODNOTANUM><ns2:PLATNOSTOD>2020-05-11</ns2:PLATNOSTOD></ns2:ZAKLADNI><ns2:ZAKLADNI><ns2:KOD>VYMERANEZPUS</ns2:KOD><ns2:HODNOTANUM>0</ns2:HODNOTANUM><ns2:PLATNOSTOD>2020-05-11</ns2:PLATNOSTOD></ns2:ZAKLADNI><ns2:PREKRYVKATUZE><ns2:KUNAZEV>Mezno</ns2:KUNAZEV><ns2:KUKOD>693839</ns2:KUKOD><ns2:VYMPREKRYV>0.12</ns2:VYMPREKRYV><ns2:DLECENTROID>0</ns2:DLECENTROID><ns2:PLATNOSTOD>2020-05-11</ns2:PLATNOSTOD><ns2:PLATNOSTDO>3000-01-01</ns2:PLATNOSTDO></ns2:PREKRYVKATUZE><ns2:PREKRYVKATUZE><ns2:KUNAZEV>Lažany u Mezna</ns2:KUNAZEV><ns2:KUKOD>693821</ns2:KUKOD><ns2:VYMPREKRYV>0.04</ns2:VYMPREKRYV><ns2:DLECENTROID>0</ns2:DLECENTROID><ns2:PLATNOSTOD>2020-05-11</ns2:PLATNOSTOD><ns2:PLATNOSTDO>3000-01-01</ns2:PLATNOSTDO></ns2:PREKRYVKATUZE><ns2:PREKRYVKATUZE><ns2:KUNAZEV>Vestec u Mezna</ns2:KUNAZEV><ns2:KUKOD>798428</ns2:KUKOD><ns2:VYMPREKRYV>30.22</ns2:VYMPREKRYV><ns2:DLECENTROID>1</ns2:DLECENTROID><ns2:PLATNOSTOD>2020-05-11</ns2:PLATNOSTOD><ns2:PLATNOSTDO>3000-01-01</ns2:PLATNOSTDO></ns2:PREKRYVKATUZE><ns2:SEZNAMEVP><ns2:EVPID>508537</ns2:EVPID><ns2:CTVEREC>730-1100</ns2:CTVEREC><ns2:ZKOD>E6403/2</ns2:ZKOD><ns2:VYMERA>207.00</ns2:VYMERA><ns2:VYMERAPREKRYV>207</ns2:VYMERAPREKRYV><ns2:GEOMETRIEEVP>POLYGON ((-736416.2647 -1104427.4961, -736416.4058 -1104429.3306, -736415.418 -1104431.5884, -736412.1725 -1104437.2328, -736409.7736 -1104441.1839, -736407.6569 -1104443.1595, -736405.5402 -1104443.5828, -736403.0002 -1104442.7362, -736401.448 -1104441.6073, -736400.0369 -1104440.3373, -736399.3313 -1104439.0673, -736399.4724 -1104437.3739, -736401.448 -1104433.4228, -736406.3869 -1104426.9317, -736408.7858 -1104424.5328, -736410.7613 -1104423.4039, -736412.5958 -1104423.4039, -736414.5713 -1104424.3917, -736415.8413 -1104425.9439, -736416.2647 -1104427.4961))</ns2:GEOMETRIEEVP><ns2:DRUHNAZEV>Skupina dřevin</ns2:DRUHNAZEV><ns2:DRUHID>4</ns2:DRUHID><ns2:PLATNOSTOD>2020-05-11</ns2:PLATNOSTOD></ns2:SEZNAMEVP><ns2:SEZNAMEVP><ns2:EVPID>508536</ns2:EVPID><ns2:CTVEREC>730-1100</ns2:CTVEREC><ns2:ZKOD>E6403/1</ns2:ZKOD><ns2:VYMERA>131.00</ns2:VYMERA><ns2:VYMERAPREKRYV>131</ns2:VYMERAPREKRYV><ns2:GEOMETRIEEVP>POLYGON ((-736395.613 -1104500.7241, -736397.2005 -1104499.9304, -736399.1849 -1104499.9304, -736401.8307 -1104500.5918, -736406.0641 -1104502.7085, -736407.5193 -1104504.296, -736408.1808 -1104506.4127, -736407.6516 -1104509.0585, -736405.4026 -1104511.3075, -736403.0214 -1104512.1012, -736400.2432 -1104511.8366, -736398.1266 -1104511.1752, -736396.1422 -1104509.72, -736394.8193 -1104508.2648, -736394.0255 -1104506.6773, -736394.1578 -1104503.8991, -736394.687 -1104502.047, -736395.613 -1104500.7241))</ns2:GEOMETRIEEVP><ns2:DRUHNAZEV>Skupina dřevin</ns2:DRUHNAZEV><ns2:DRUHID>4</ns2:DRUHID><ns2:PLATNOSTOD>2020-05-11</ns2:PLATNOSTOD></ns2:SEZNAMEVP><ns2:LFA><ns2:LFAKOD>O3</ns2:LFAKOD><ns2:VYMPREKRYV>30.38</ns2:VYMPREKRYV><ns2:PLATNOSTOD>2020-05-11</ns2:PLATNOSTOD></ns2:LFA><ns2:VYNOSHLADINA><ns2:VYNOSHLADINAKOD>1</ns2:VYNOSHLADINAKOD><ns2:VYMPREKRYV>7.46</ns2:VYMPREKRYV><ns2:PLATNOSTOD>2020-01-01</ns2:PLATNOSTOD></ns2:VYNOSHLADINA><ns2:VYNOSHLADINA><ns2:VYNOSHLADINAKOD>2</ns2:VYNOSHLADINAKOD><ns2:VYMPREKRYV>22.8</ns2:VYMPREKRYV><ns2:PLATNOSTOD>2020-01-01</ns2:PLATNOSTOD></ns2:VYNOSHLADINA><ns2:BPEJ><ns2:BPEJKOD>00099</ns2:BPEJKOD><ns2:VYMPREKRYV>0.06</ns2:VYMPREKRYV><ns2:PLATNOSTOD>2020-05-11</ns2:PLATNOSTOD></ns2:BPEJ><ns2:BPEJ><ns2:BPEJKOD>83421</ns2:BPEJKOD><ns2:VYMPREKRYV>13.07</ns2:VYMPREKRYV><ns2:PLATNOSTOD>2020-05-11</ns2:PLATNOSTOD></ns2:BPEJ><ns2:BPEJ><ns2:BPEJKOD>83424</ns2:BPEJKOD><ns2:VYMPREKRYV>9.67</ns2:VYMPREKRYV><ns2:PLATNOSTOD>2020-05-11</ns2:PLATNOSTOD></ns2:BPEJ><ns2:BPEJ><ns2:BPEJKOD>83716</ns2:BPEJKOD><ns2:VYMPREKRYV>0.45</ns2:VYMPREKRYV><ns2:PLATNOSTOD>2020-05-11</ns2:PLATNOSTOD></ns2:BPEJ><ns2:BPEJ><ns2:BPEJKOD>85011</ns2:BPEJKOD><ns2:VYMPREKRYV>5.43</ns2:VYMPREKRYV><ns2:PLATNOSTOD>2020-05-11</ns2:PLATNOSTOD></ns2:BPEJ><ns2:BPEJ><ns2:BPEJKOD>86811</ns2:BPEJKOD><ns2:VYMPREKRYV>1.7</ns2:VYMPREKRYV><ns2:PLATNOSTOD>2020-05-11</ns2:PLATNOSTOD></ns2:BPEJ><ns2:OPATRENIEROZE2G><ns2:EROZOHRKOD>MEO</ns2:EROZOHRKOD><ns2:PLATNOSTOD>2020-01-01</ns2:PLATNOSTOD><ns2:PLATNOSTDO>3000-01-01</ns2:PLATNOSTDO></ns2:OPATRENIEROZE2G></ns2:DPB></ns2:Response></Data></ESBServerEnvelopeResponse></soap:Body></soap:Envelope>